{
  "about": {
    "js": "/public/about.a33aac8decc63727237b.js"
  },
  "addphotopoint": {
    "js": "/public/addphotopoint.9973f8f99411a8967910.js",
    "css": "/public/addphotopoint.9973f8f99411a8967910.css"
  },
  "adminuserinvite": {
    "js": "/public/adminuserinvite.ac126c209df8fc0f5577.js"
  },
  "approvedialog": {
    "js": "/public/approvedialog.4e7f8358435732146173.js"
  },
  "creategroup": {
    "js": "/public/creategroup.ace078cc2b3fba5b070a.js",
    "css": "/public/creategroup.ace078cc2b3fba5b070a.css"
  },
  "createhubstory": {
    "js": "/public/createhubstory.d8c65d31f3ea4fdfbe2e.js",
    "css": "/public/createhubstory.d8c65d31f3ea4fdfbe2e.css"
  },
  "createlayer": {
    "js": "/public/createlayer.90b4816b33d8ed297c11.js",
    "css": "/public/createlayer.90b4816b33d8ed297c11.css"
  },
  "createremotelayer": {
    "js": "/public/createremotelayer.24d4815758f4c2753dae.js",
    "css": "/public/createremotelayer.24d4815758f4c2753dae.css"
  },
  "createuserstory": {
    "js": "/public/createuserstory.4f292a613594a96fa6fd.js",
    "css": "/public/createuserstory.4f292a613594a96fa6fd.css"
  },
  "edithubstory": {
    "js": "/public/edithubstory.f3fcc27bf724e064946b.js",
    "css": "/public/edithubstory.f3fcc27bf724e064946b.css"
  },
  "edituserstory": {
    "js": "/public/edituserstory.681249d875287db2566f.js",
    "css": "/public/edituserstory.681249d875287db2566f.css"
  },
  "emailconfirmation": {
    "js": "/public/emailconfirmation.5ce81f097012474f3c2e.js"
  },
  "embedmap": {
    "js": "/public/embedmap.95a333663e4efef463eb.js",
    "css": "/public/embedmap.95a333663e4efef463eb.css"
  },
  "error": {
    "js": "/public/error.b79093570bc6f3cbc501.js"
  },
  "explore": {
    "js": "/public/explore.da9b2195e772be1e8986.js",
    "css": "/public/explore.da9b2195e772be1e8986.css"
  },
  "featureinfo": {
    "js": "/public/featureinfo.057552d439345ac7ea08.js",
    "css": "/public/featureinfo.057552d439345ac7ea08.css"
  },
  "groupadmin": {
    "js": "/public/groupadmin.ad84b9bd1f3ad559e3f4.js",
    "css": "/public/groupadmin.ad84b9bd1f3ad559e3f4.css"
  },
  "groupinfo": {
    "js": "/public/groupinfo.59090611981e4d8a2a12.js",
    "css": "/public/groupinfo.59090611981e4d8a2a12.css"
  },
  "groups": {
    "js": "/public/groups.ac640876a4ad263d189a.js",
    "css": "/public/groups.ac640876a4ad263d189a.css"
  },
  "home": {
    "js": "/public/home.2de46ee2bf2e8b572e27.js",
    "css": "/public/home.2de46ee2bf2e8b572e27.css"
  },
  "hubadmin": {
    "js": "/public/hubadmin.3e296554c67e674af608.js"
  },
  "hubbuilder": {
    "js": "/public/hubbuilder.770f4bbb102835977c76.js"
  },
  "hubinfo": {
    "js": "/public/hubinfo.d3bd79871e477a804550.js",
    "css": "/public/hubinfo.d3bd79871e477a804550.css"
  },
  "hubmap": {
    "js": "/public/hubmap.64826aba6be7ecc9e4f3.js",
    "css": "/public/hubmap.64826aba6be7ecc9e4f3.css"
  },
  "hubresources": {
    "js": "/public/hubresources.8f42601cd2977ae16442.js",
    "css": "/public/hubresources.8f42601cd2977ae16442.css"
  },
  "hubs": {
    "js": "/public/hubs.3b82c77edbb384461458.js",
    "css": "/public/hubs.3b82c77edbb384461458.css"
  },
  "hubstories": {
    "js": "/public/hubstories.6707b368be9c3d2f186a.js",
    "css": "/public/hubstories.6707b368be9c3d2f186a.css"
  },
  "hubstory": {
    "js": "/public/hubstory.1735b5b52f328d98273f.js",
    "css": "/public/hubstory.1735b5b52f328d98273f.css"
  },
  "journalists": {
    "js": "/public/journalists.b6784dadd4270c9608c7.js"
  },
  "layeradmin": {
    "js": "/public/layeradmin.dd845edc04c7f0d75768.js",
    "css": "/public/layeradmin.dd845edc04c7f0d75768.css"
  },
  "layerinfo": {
    "js": "/public/layerinfo.ebb1379399ba56155783.js",
    "css": "/public/layerinfo.ebb1379399ba56155783.css"
  },
  "layermap": {
    "js": "/public/layermap.c748509723673a1da780.js",
    "css": "/public/layermap.c748509723673a1da780.css"
  },
  "layers": {
    "js": "/public/layers.54b27592301b5f8f4819.js",
    "css": "/public/layers.54b27592301b5f8f4819.css"
  },
  "locales": {
    "js": "/public/locales.0810f8db56e9c59acdf1.js"
  },
  "login": {
    "js": "/public/login.ecff34c22635fc28df5d.js"
  },
  "map": {
    "js": "/public/map.198d9f57321e3f8383b4.js",
    "css": "/public/map.198d9f57321e3f8383b4.css"
  },
  "mapboxgl": {
    "js": "/public/mapboxgl.8f607e3150b76f0035ee.js"
  },
  "mapedit": {
    "js": "/public/mapedit.85f404ab4151e944e220.js",
    "css": "/public/mapedit.85f404ab4151e944e220.css"
  },
  "maps": {
    "js": "/public/maps.aa33f90d4b189599af41.js",
    "css": "/public/maps.aa33f90d4b189599af41.css"
  },
  "passwordreset": {
    "js": "/public/passwordreset.248cdb0cda5be2319c01.js"
  },
  "pendingconfirmation": {
    "js": "/public/pendingconfirmation.837887381f6d7553d746.js"
  },
  "privacy": {
    "js": "/public/privacy.a26ceeba6ea5dd046fb7.js"
  },
  "search": {
    "js": "/public/search.3d1f33edb2d05a56dfc3.js",
    "css": "/public/search.3d1f33edb2d05a56dfc3.css"
  },
  "services": {
    "js": "/public/services.044295f220ab128905ea.js"
  },
  "signup": {
    "js": "/public/signup.78d6ad965fe65fde35ec.js"
  },
  "staticmap": {
    "js": "/public/staticmap.b57245029c40248b5084.js",
    "css": "/public/staticmap.b57245029c40248b5084.css"
  },
  "stories": {
    "js": "/public/stories.dda4798f79aae1812a7a.js",
    "css": "/public/stories.dda4798f79aae1812a7a.css"
  },
  "terms": {
    "js": "/public/terms.0e8a4f33bac19ccb4155.js"
  },
  "usergroups": {
    "js": "/public/usergroups.c503809254cad1a19723.js",
    "css": "/public/usergroups.c503809254cad1a19723.css"
  },
  "userhubs": {
    "js": "/public/userhubs.e710dc292e141a27d155.js",
    "css": "/public/userhubs.e710dc292e141a27d155.css"
  },
  "usermap": {
    "js": "/public/usermap.476853d4c3d7d46d402a.js",
    "css": "/public/usermap.476853d4c3d7d46d402a.css"
  },
  "usermaps": {
    "js": "/public/usermaps.fbfe6cc58c15a35944c1.js",
    "css": "/public/usermaps.fbfe6cc58c15a35944c1.css"
  },
  "usersettings": {
    "js": "/public/usersettings.e97117d1f46dc14f357c.js"
  },
  "userstories": {
    "js": "/public/userstories.db6f6b81022259603744.js",
    "css": "/public/userstories.db6f6b81022259603744.css"
  },
  "userstory": {
    "js": "/public/userstory.19a71ce90b9fcc9b741b.js",
    "css": "/public/userstory.19a71ce90b9fcc9b741b.css"
  },
  "vendor": {
    "js": "/public/vendor.1a28e65ea0dd6f9a2501.js"
  },
  "metadata": {
    "version": "0.12.15"
  },
  "homedemo": {
    "js": "/public/homedemo.4f33e5f49134ca06f1e0.js",
    "css": "/public/homedemo.4f33e5f49134ca06f1e0.css"
  },
  "pageedit": {
    "js": "/public/pageedit.06d62484d5d7a9d59746.js"
  },
  "searchindexadmin": {
    "js": "/public/searchindexadmin.f5a3967fd707234c9d5f.js"
  },
  "homepro": {
    "js": "/public/homepro.7cf8306d0666c9a320f1.js",
    "css": "/public/homepro.7cf8306d0666c9a320f1.css"
  },
  "auth0profile": {
    "js": "/public/auth0profile.676cf5ba52fbed7ae98a.js"
  },
  "auth0error": {
    "js": "/public/auth0error.b337a393584a00a4f8b6.js"
  },
  "auth0login": {
    "js": "/public/auth0login.d64bda44bbd23e97580c.js"
  },
  "allmaps": {
    "js": "/public/allmaps.cdae6d9159ae90dc7970.js",
    "css": "/public/allmaps.cdae6d9159ae90dc7970.css"
  },
  "allstories": {
    "js": "/public/allstories.62b6c161a587425fa2f5.js",
    "css": "/public/allstories.62b6c161a587425fa2f5.css"
  },
  "alllayers": {
    "js": "/public/alllayers.e53e3ee58d6ddc4bb8a0.js",
    "css": "/public/alllayers.e53e3ee58d6ddc4bb8a0.css"
  },
  "allhubs": {
    "js": "/public/allhubs.fd10ec6cbea5b57bc112.js",
    "css": "/public/allhubs.fd10ec6cbea5b57bc112.css"
  },
  "allgroups": {
    "js": "/public/allgroups.ff7789cac672d8a0cf55.js",
    "css": "/public/allgroups.ff7789cac672d8a0cf55.css"
  },
  "auth0invite": {
    "js": "/public/auth0invite.21f58bd1e5b222bf586a.js"
  },
  "layerreplace": {
    "js": "/public/layerreplace.0093778272b166eb824a.js",
    "css": "/public/layerreplace.0093778272b166eb824a.css"
  }
}